Metadata-Version: 2.1
Name: probable
Version: 0.1
Summary: Gaussian and Binomial distributions
Home-page: UNKNOWN
Author: Oluwaseun Ajayi
Author-email: oluwaseunaajayi@student.oauife.edu.ng
License: UNKNOWN
Platform: UNKNOWN
